a2a_min/__init__.py
a2a_min/agent_adapter.py
a2a_min/client.py
a2a_min/server.py
a2a_min/task_manager.py
a2a_min/types.py
a2a_min/base/__init__.py
a2a_min/base/types.py
a2a_min/base/client/__init__.py
a2a_min/base/client/card_resolver.py
a2a_min/base/client/client.py
a2a_min/base/server/__init__.py
a2a_min/base/server/server.py
a2a_min/base/server/task_manager.py
a2a_min/base/server/utils.py
a2a_min/base/utils/in_memory_cache.py
a2a_min/base/utils/push_notification_auth.py
a2a_min/examples/multimodal_agent_example.py
a2a_min/examples/streaming_agent_example.py
a2a_min/examples/base/agent_task_manager.py
a2a_min/examples/base/dummy_agent.py
a2a_min/examples/base/server_example.py
a2a_min/examples/echo_a2a/echo_a2a_client.py
a2a_min/examples/echo_a2a/echo_a2a_server.py
a2a_min/middleware/__init__.py
a2a_min/middleware/debug_middleware.py
a2a_min/middleware/logging_middleware.py
a2a_min/middleware/metrics_middleware.py
a2a_min/middleware/middleware.py
a2a_min-0.1.0.dist-info/licenses/LICENSE
a2a_min-0.1.0.dist-info/METADATA
a2a_min-0.1.0.dist-info/WHEEL
a2a_min-0.1.0.dist-info/top_level.txt
a2a_min-0.1.0.dist-info/RECORD
