Metadata-Version: 2.4
Name: a2a-min
Version: 0.1.0
Summary: Agent to Agent (A2A) minimalistic Python SDK
Author: A2A SDK Team
Project-URL: Homepage, https://github.com/pcingola/a2a_min
Project-URL: Bug Tracker, https://github.com/pcingola/a2a_min/issues
Classifier: Programming Language :: Python :: 3
Classifier: Programming Language :: Python :: 3.12
Classifier: License :: OSI Approved :: MIT License
Classifier: Operating System :: OS Independent
Classifier: Development Status :: 4 - Beta
Classifier: Intended Audience :: Developers
Classifier: Topic :: Software Development :: Libraries :: Python Modules
Requires-Python: >=3.12.2
License-File: LICENSE
Requires-Dist: dotenv>=0.9.9
Requires-Dist: httpx>=0.28.1
Requires-Dist: httpx-sse>=0.4.0
Requires-Dist: ipykernel>=6.29.5
Requires-Dist: jwcrypto>=1.5.6
Requires-Dist: jwt>=1.3.1
Requires-Dist: pydantic>=2.11.3
Requires-Dist: pyjwt>=2.10.1
Requires-Dist: ruff>=0.11.5
Requires-Dist: sse-starlette>=2.2.1
Requires-Dist: starlette>=0.46.2
Requires-Dist: uvicorn>=0.34.1
Dynamic: license-file
